LICENSE
MANIFEST.in
README.rst
setup.py
django_sendsms_admin.egg-info/PKG-INFO
django_sendsms_admin.egg-info/SOURCES.txt
django_sendsms_admin.egg-info/dependency_links.txt
django_sendsms_admin.egg-info/not-zip-safe
django_sendsms_admin.egg-info/requires.txt
django_sendsms_admin.egg-info/top_level.txt
sendsms_admin/__init__.py
sendsms_admin/admin.py
sendsms_admin/backend.py
sendsms_admin/models.py
sendsms_admin/migrations/0001_initial.py
sendsms_admin/migrations/__init__.py