Metadata-Version: 1.0
Name: django-sendsms-admin
Version: 0.1.0
Summary: A database delivery backend for django-sendsms (for debugging).
Home-page: http://github.com/stefanfoulis/django-sendsms-admin
Author: Stefan Foulis
Author-email: stefan.foulis@gmail.com
License: BSD
Platform: OS Independent
Classifier: Development Status :: 3 - Alpha
Classifier: Framework :: Django
Classifier: Intended Audience :: Developers
Classifier: License :: OSI Approved :: BSD License
Classifier: Operating System :: OS Independent
Classifier: Programming Language :: Python
Classifier: Topic :: Internet :: WWW/HTTP
